CONTRIBUTING.md
LICENSE.txt
MANIFEST.in
README.rst
cdnupload.py
setup.cfg
setup.py
cdnupload.egg-info/PKG-INFO
cdnupload.egg-info/SOURCES.txt
cdnupload.egg-info/dependency_links.txt
cdnupload.egg-info/entry_points.txt
cdnupload.egg-info/requires.txt
cdnupload.egg-info/top_level.txt
tests/test_delete.py
tests/test_file_destination.py
tests/test_file_source.py
tests/test_s3_destination.py
tests/test_upload.py