Metadata-Version: 1.1
Name: cdnupload
Version: 1.0.0
Summary: Upload static files from given source directory to destination directory or Amazon S3 bucket, with content-based hash in filenames for versioning.
Home-page: https://cdnupload.com/
Author: Ben Hoyt
Author-email: benhoyt@gmail.com
License: Multi-licensed: AGPLv3 and Commercial
Platform: UNKNOWN
Classifier: Development Status :: 5 - Production/Stable
Classifier: Intended Audience :: Developers
Classifier: Operating System :: OS Independent
Classifier: License :: Other/Proprietary License
Classifier: Programming Language :: Python
Classifier: Programming Language :: Python
Classifier: Programming Language :: Python :: 2
Classifier: Programming Language :: Python :: 2.7
Classifier: Programming Language :: Python :: 3
Classifier: Programming Language :: Python :: 3.4
Classifier: Programming Language :: Python :: 3.5
Classifier: Programming Language :: Python :: 3.6
Classifier: Topic :: Internet :: WWW/HTTP
